dorico_mcp/__init__.py
dorico_mcp/client.py
dorico_mcp/commands.py
dorico_mcp/models.py
dorico_mcp/server.py
dorico_mcp/tools/__init__.py
dorico_mcp/tools/instruments.py
dorico_mcp_server-0.3.0.dist-info/METADATA
dorico_mcp_server-0.3.0.dist-info/WHEEL
dorico_mcp_server-0.3.0.dist-info/entry_points.txt
dorico_mcp_server-0.3.0.dist-info/RECORD
