Metadata-Version: 2.4
Name: dorico-mcp-server
Version: 0.3.0
Summary: MCP Server for controlling Dorico via Claude Desktop - A gift for composition majors
Project-URL: Homepage, https://github.com/yourusername/dorico-mcp-server
Project-URL: Documentation, https://github.com/yourusername/dorico-mcp-server#readme
Project-URL: Repository, https://github.com/yourusername/dorico-mcp-server.git
Project-URL: Issues, https://github.com/yourusername/dorico-mcp-server/issues
Author-email: Your Name <your.email@example.com>
License-Expression: MIT
Keywords: ai,composition,dorico,mcp,music,notation
Classifier: Development Status :: 3 - Alpha
Classifier: Intended Audience :: End Users/Desktop
Classifier: License :: OSI Approved :: MIT License
Classifier: Programming Language :: Python :: 3
Classifier: Programming Language :: Python :: 3.11
Classifier: Programming Language :: Python :: 3.12
Classifier: Topic :: Artistic Software
Classifier: Topic :: Multimedia :: Sound/Audio
Requires-Python: >=3.11
Requires-Dist: httpx>=0.27.0
Requires-Dist: mcp>=1.0.0
Requires-Dist: music21>=9.1.0
Requires-Dist: pydantic>=2.0
Requires-Dist: websockets>=12.0
Provides-Extra: dev
Requires-Dist: mypy>=1.10; extra == 'dev'
Requires-Dist: pytest-asyncio>=0.23; extra == 'dev'
Requires-Dist: pytest-cov>=4.0; extra == 'dev'
Requires-Dist: pytest>=8.0; extra == 'dev'
Requires-Dist: ruff>=0.4; extra == 'dev'
